template_creator.py
assignment_template_creator-1.0.5.dist-info/METADATA
assignment_template_creator-1.0.5.dist-info/WHEEL
assignment_template_creator-1.0.5.dist-info/entry_points.txt
assignment_template_creator-1.0.5.dist-info/top_level.txt
assignment_template_creator-1.0.5.dist-info/RECORD
