Metadata-Version: 2.1
Name: assignment-template-creator
Version: 1.0.5
Summary: the ultimate tool fpor CS assignment template generatipon.
Home-page: UNKNOWN
Author: stasik
Author-email: UNKNOWN
License: UNKNOWN
Platform: UNKNOWN
Classifier: Programming Language :: Python :: 3
Requires-Dist: colorama
Requires-Dist: python-docx
